erpbrasil.edoc.gen-0.1.0-py3.8-nspkg.pth
erpbrasil/edoc/__init__.py
erpbrasil/edoc/gen/__init__.py
erpbrasil/edoc/gen/__main__.py
erpbrasil/edoc/gen/cli.py
erpbrasil/edoc/gen/download_schema.py
erpbrasil/edoc/gen/generate_odoo.py
erpbrasil/edoc/gen/generate_python.py
erpbrasil.edoc.gen-0.1.0.dist-info/AUTHORS.rst
erpbrasil.edoc.gen-0.1.0.dist-info/LICENSE
erpbrasil.edoc.gen-0.1.0.dist-info/METADATA
erpbrasil.edoc.gen-0.1.0.dist-info/WHEEL
erpbrasil.edoc.gen-0.1.0.dist-info/entry_points.txt
erpbrasil.edoc.gen-0.1.0.dist-info/namespace_packages.txt
erpbrasil.edoc.gen-0.1.0.dist-info/top_level.txt
erpbrasil.edoc.gen-0.1.0.dist-info/RECORD
