Metadata-Version: 2.1
Name: erpbrasil.edoc.gen
Version: 0.1.0
Summary: Generate Brazil Edoc with GenerateDS
Home-page: https://github.com/mileo/erpbrail.edoc.gen
Author: Luis Felipe Mileo
Author-email: mileo@kmee.com.br
License: MIT
Project-URL: Documentation, https://erpbrailedocgen.readthedocs.io/
Project-URL: Changelog, https://erpbrailedocgen.readthedocs.io/en/latest/changelog.html
Project-URL: Issue Tracker, https://github.com/mileo/erpbrail.edoc.gen/issues
Platform: UNKNOWN
Classifier: Development Status :: 5 - Production/Stable
Classifier: Intended Audience :: Developers
Classifier: License :: OSI Approved :: MIT License
Classifier: Operating System :: Unix
Classifier: Operating System :: POSIX
Classifier: Operating System :: Microsoft :: Windows
Classifier: Programming Language :: Python
Classifier: Programming Language :: Python :: 2.7
Classifier: Programming Language :: Python :: 3
Classifier: Programming Language :: Python :: 3.5
Classifier: Programming Language :: Python :: 3.6
Classifier: Programming Language :: Python :: 3.7
Classifier: Programming Language :: Python :: 3.8
Classifier: Programming Language :: Python :: Implementation :: CPython
Classifier: Programming Language :: Python :: Implementation :: PyPy
Classifier: Topic :: Utilities
Requires-Python: >=2.7, !=3.0.*, !=3.1.*, !=3.2.*, !=3.3.*, !=3.4.*
Requires-Dist: click
Requires-Dist: click-log
Requires-Dist: generateDS
